thornfield/__init__.py
thornfield/cacher.py
thornfield/caching_data.py
thornfield/constants.py
thornfield/errors.py
thornfield/postgresql_key_value_adapter.py
thornfield/typing.py
thornfield/validators.py
thornfield/cache_factories/__init__.py
thornfield/cache_factories/cache_factory.py
thornfield/cache_factories/postgresql_cache_factory.py
thornfield/cache_factories/redis_cache_factory.py
thornfield/caches/__init__.py
thornfield/caches/cache.py
thornfield/caches/cache_compression_decorator.py
thornfield/caches/cache_serialization_decorator.py
thornfield/caches/memory_cache.py
thornfield/caches/postgresql_cache.py
thornfield/caches/redis_cache.py
thornfield/caches/volatile_value.py
thornfield-1.5.1.dist-info/LICENSE
thornfield-1.5.1.dist-info/METADATA
thornfield-1.5.1.dist-info/WHEEL
thornfield-1.5.1.dist-info/top_level.txt
thornfield-1.5.1.dist-info/RECORD
