Metadata-Version: 2.1
Name: thornfield
Version: 1.5.1
Summary: Advanced caching in python
Home-page: https://github.com/drorvinkler/thornfield
Author: Dror A. Vinkler
License: MIT
Platform: UNKNOWN
Classifier: Programming Language :: Python :: 3
Classifier: License :: OSI Approved :: MIT License
Classifier: Operating System :: OS Independent
Requires-Python: >=3.7
